MANIFEST.in
README.md
setup.py
sphinx_3dr_theme/__init__.py
sphinx_3dr_theme/__init__.pyc
sphinx_3dr_theme/footer.html
sphinx_3dr_theme/layout.html
sphinx_3dr_theme/search.html
sphinx_3dr_theme/searchbox.html
sphinx_3dr_theme/theme.conf
sphinx_3dr_theme.egg-info/PKG-INFO
sphinx_3dr_theme.egg-info/SOURCES.txt
sphinx_3dr_theme.egg-info/dependency_links.txt
sphinx_3dr_theme.egg-info/not-zip-safe
sphinx_3dr_theme.egg-info/pbr.json
sphinx_3dr_theme.egg-info/requires.txt
sphinx_3dr_theme.egg-info/top_level.txt
sphinx_3dr_theme/static/css/__init__.py
sphinx_3dr_theme/static/css/__init__.pyc
sphinx_3dr_theme/static/css/style.css
sphinx_3dr_theme/static/css/style.css.map
sphinx_3dr_theme/static/fonts/FontAwesome.otf
sphinx_3dr_theme/static/fonts/HelveticaNeue-Light.eot
sphinx_3dr_theme/static/fonts/HelveticaNeue-Light.svg
sphinx_3dr_theme/static/fonts/HelveticaNeue-Light.ttf
sphinx_3dr_theme/static/fonts/HelveticaNeue-Light.woff
sphinx_3dr_theme/static/fonts/HelveticaNeue.eot
sphinx_3dr_theme/static/fonts/HelveticaNeue.svg
sphinx_3dr_theme/static/fonts/HelveticaNeue.ttf
sphinx_3dr_theme/static/fonts/HelveticaNeue.woff
sphinx_3dr_theme/static/fonts/HelveticaNeueBold.ttf
sphinx_3dr_theme/static/fonts/HelveticaNeueLight.ttf
sphinx_3dr_theme/static/fonts/__init__.py
sphinx_3dr_theme/static/fonts/__init__.pyc
sphinx_3dr_theme/static/fonts/copenhagen_bold-webfont.eot
sphinx_3dr_theme/static/fonts/copenhagen_bold-webfont.svg
sphinx_3dr_theme/static/fonts/copenhagen_bold-webfont.ttf
sphinx_3dr_theme/static/fonts/copenhagen_bold-webfont.woff
sphinx_3dr_theme/static/fonts/copenhagen_bold-webfont.woff2
sphinx_3dr_theme/static/fonts/copenhagen_light-webfont.eot
sphinx_3dr_theme/static/fonts/copenhagen_light-webfont.svg
sphinx_3dr_theme/static/fonts/copenhagen_light-webfont.ttf
sphinx_3dr_theme/static/fonts/copenhagen_light-webfont.woff
sphinx_3dr_theme/static/fonts/copenhagen_light-webfont.woff2
sphinx_3dr_theme/static/fonts/copenhagen_regular-webfont.eot
sphinx_3dr_theme/static/fonts/copenhagen_regular-webfont.svg
sphinx_3dr_theme/static/fonts/copenhagen_regular-webfont.ttf
sphinx_3dr_theme/static/fonts/copenhagen_regular-webfont.woff
sphinx_3dr_theme/static/fonts/copenhagen_regular-webfont.woff2
sphinx_3dr_theme/static/fonts/fontawesome-webfont.eot
